{
  "category": "Дизайн",
  "name": "Альтро МФ",
  "slug": "altro-mf",
  "source_url": "https://dveri-lord.ru/product/altro-mf/",
  "details_text": "Межкомнатная дверь с алюминиевым молдингом и фрезеровкой\nВарианты покрытия:\nПВХ\nЭмаль\nВарианты цветов молдинга:\nЧерный\nБелый\nСеребро\nЗолото\nВарианты оформления проёма двери:\nКороб Telescope\nКомпланарная система\nСтандартные размеры:\nШирина двери: 500/600/700/800/900 мм\nВысота двери: 1900/2000 мм\nТолщина двери: 38 мм\nНестандартные размеры:\nШирина двери: до 1100 мм (с шагом 10 мм)\nВысота двери: до 2300 мм (с шагом 10 мм)",
  "image_urls": [
    "https://dveri-lord.ru/wp-content/uploads/2023/06/altro-mf1.png",
    "https://dveri-lord.ru/wp-content/uploads/2023/06/altro-mf2.png",
    "https://dveri-lord.ru/wp-content/uploads/2023/06/altro-mf3.png",
    "https://dveri-lord.ru/wp-content/uploads/2023/06/altro-mf4.png",
    "https://dveri-lord.ru/wp-content/uploads/2023/06/altro-mf5.png",
    "https://dveri-lord.ru/wp-content/uploads/2023/06/altro-mf6.png",
    "https://dveri-lord.ru/wp-content/uploads/2023/06/altro-mf7.png",
    "https://dveri-lord.ru/wp-content/uploads/2023/06/altro-mf8.png",
    "https://dveri-lord.ru/wp-content/uploads/2023/06/altro-mf9.png",
    "https://dveri-lord.ru/wp-content/uploads/2023/06/altro-mf10.png",
    "https://dveri-lord.ru/wp-content/uploads/2023/06/altro-mf11.png",
    "https://dveri-lord.ru/wp-content/uploads/2023/06/altro-mf12.png",
    "https://dveri-lord.ru/wp-content/uploads/2023/06/altro-mf13.png",
    "https://dveri-lord.ru/wp-content/uploads/2023/06/altro-mf14.png",
    "https://dveri-lord.ru/wp-content/uploads/2023/06/altro-mf15.png",
    "https://dveri-lord.ru/wp-content/uploads/2023/06/altro-mf16.png",
    "https://dveri-lord.ru/wp-content/uploads/2023/06/altro-mf17.png",
    "https://dveri-lord.ru/wp-content/uploads/2023/06/altro-mf18.png",
    "https://dveri-lord.ru/wp-content/uploads/2023/06/altro-mf19.png",
    "https://dveri-lord.ru/wp-content/uploads/2023/06/altro-mf20.png"
  ],
  "local_images": [
    "data\\lord\\Дизайн\\Альтро МФ\\images\\01.png",
    "data\\lord\\Дизайн\\Альтро МФ\\images\\02.png",
    "data\\lord\\Дизайн\\Альтро МФ\\images\\03.png",
    "data\\lord\\Дизайн\\Альтро МФ\\images\\04.png",
    "data\\lord\\Дизайн\\Альтро МФ\\images\\05.png",
    "data\\lord\\Дизайн\\Альтро МФ\\images\\06.png",
    "data\\lord\\Дизайн\\Альтро МФ\\images\\07.png",
    "data\\lord\\Дизайн\\Альтро МФ\\images\\08.png",
    "data\\lord\\Дизайн\\Альтро МФ\\images\\09.png",
    "data\\lord\\Дизайн\\Альтро МФ\\images\\10.png",
    "data\\lord\\Дизайн\\Альтро МФ\\images\\11.png",
    "data\\lord\\Дизайн\\Альтро МФ\\images\\12.png",
    "data\\lord\\Дизайн\\Альтро МФ\\images\\13.png",
    "data\\lord\\Дизайн\\Альтро МФ\\images\\14.png",
    "data\\lord\\Дизайн\\Альтро МФ\\images\\15.png",
    "data\\lord\\Дизайн\\Альтро МФ\\images\\16.png",
    "data\\lord\\Дизайн\\Альтро МФ\\images\\17.png",
    "data\\lord\\Дизайн\\Альтро МФ\\images\\18.png",
    "data\\lord\\Дизайн\\Альтро МФ\\images\\19.png",
    "data\\lord\\Дизайн\\Альтро МФ\\images\\20.png"
  ]
}