{
  "category": "Минимализм",
  "name": "Атриум",
  "slug": "atrium",
  "source_url": "https://dveri-lord.ru/product/atrium/",
  "details_text": "Межкомнатная дверь со вставкой из стекла и алюминиевой кромкой\nВарианты покрытия:\nПВХ\nВарианты цветов кромки:\nЧерный\nБелый\nСеребро\nЗолото\nВарианты остекления:\nЗеркало: Серебро, Графит, Бронза.\nЛакобель: Ультрабелый, Белый, Бежевый, Шамуа, Коричневый, Черный.\nВарианты оформления проёма двери:\nКороб Telescope\nКомпланарная система\nСтандартные размеры:\nШирина двери: 500/600/700/800/900 мм\nВысота двери: 1900/2000 мм\nТолщина двери: 38 мм\nНестандартные размеры:\nШирина двери: до 1100 мм (с шагом 10 мм)\nВысота двери: до 2300 мм (с шагом 10 мм)",
  "image_urls": [
    "https://dveri-lord.ru/wp-content/uploads/2021/10/atrium-slajd1.jpg",
    "https://dveri-lord.ru/wp-content/uploads/2021/10/atrium-slajd3.jpg",
    "https://dveri-lord.ru/wp-content/uploads/2021/10/atrium-slajd2.jpg",
    "https://dveri-lord.ru/wp-content/uploads/2021/10/atrium-1.png",
    "https://dveri-lord.ru/wp-content/uploads/2021/10/atrium-2.png",
    "https://dveri-lord.ru/wp-content/uploads/2021/10/atrium-3.png",
    "https://dveri-lord.ru/wp-content/uploads/2021/10/atrium-4.png",
    "https://dveri-lord.ru/wp-content/uploads/2021/10/atrium-5.png",
    "https://dveri-lord.ru/wp-content/uploads/2021/10/atrium-6.png",
    "https://dveri-lord.ru/wp-content/uploads/2022/03/atrium-11.png",
    "https://dveri-lord.ru/wp-content/uploads/2022/03/atrium-12.png",
    "https://dveri-lord.ru/wp-content/uploads/2021/10/atrium-light-1.png",
    "https://dveri-lord.ru/wp-content/uploads/2021/10/atrium-light-2.png",
    "https://dveri-lord.ru/wp-content/uploads/2021/10/atrium-light-3.png",
    "https://dveri-lord.ru/wp-content/uploads/2021/10/atrium-light-4.png",
    "https://dveri-lord.ru/wp-content/uploads/2021/10/atrium-light-5.png",
    "https://dveri-lord.ru/wp-content/uploads/2021/10/atrium-light-6-2.png",
    "https://dveri-lord.ru/wp-content/uploads/2021/10/atrium-light-7.png",
    "https://dveri-lord.ru/wp-content/uploads/2021/10/atrium-light-8.png"
  ],
  "local_images": [
    "data\\lord\\Минимализм\\Атриум\\images\\01.jpg",
    "data\\lord\\Минимализм\\Атриум\\images\\02.jpg",
    "data\\lord\\Минимализм\\Атриум\\images\\03.jpg",
    "data\\lord\\Минимализм\\Атриум\\images\\04.png",
    "data\\lord\\Минимализм\\Атриум\\images\\05.png",
    "data\\lord\\Минимализм\\Атриум\\images\\06.png",
    "data\\lord\\Минимализм\\Атриум\\images\\07.png",
    "data\\lord\\Минимализм\\Атриум\\images\\08.png",
    "data\\lord\\Минимализм\\Атриум\\images\\09.png",
    "data\\lord\\Минимализм\\Атриум\\images\\10.png",
    "data\\lord\\Минимализм\\Атриум\\images\\11.png",
    "data\\lord\\Минимализм\\Атриум\\images\\12.png",
    "data\\lord\\Минимализм\\Атриум\\images\\13.png",
    "data\\lord\\Минимализм\\Атриум\\images\\14.png",
    "data\\lord\\Минимализм\\Атриум\\images\\15.png",
    "data\\lord\\Минимализм\\Атриум\\images\\16.png",
    "data\\lord\\Минимализм\\Атриум\\images\\17.png",
    "data\\lord\\Минимализм\\Атриум\\images\\18.png",
    "data\\lord\\Минимализм\\Атриум\\images\\19.png"
  ]
}